StudentDataBulkImporter
