Metadata-Version: 2.1
Name: StudentDataBulkImporter
Version: 0.1.1
Summary: SDK for importing and managing student data in bulk.
Author: Rohan Dixit
Author-email: rohan.dixit@samarth.ac.in
Classifier: Programming Language :: Python :: 3
Classifier: License :: OSI Approved :: MIT License
Classifier: Operating System :: OS Independent
Requires-Python: >=3.6
Requires-Dist: requests
Requires-Dist: sqlalchemy
Requires-Dist: pandas
Requires-Dist: pymysql
